<?xml version="1.0" encoding="utf-8" ?>
<template>
  <authors>
    <author>
      <name>Elze de Groot</name>
      <contact>groot@nictiz.nl</contact>
  </author>
  </authors>
  <title>Complicatie infectie bij hulpmiddel</title>
  <description>
    Dit template kan worden gebruikt om een complicatie van een infectie bij een hulpmiddel vast te leggen.
  </description>
  <snomedVersion>2021-03-31</snomedVersion>
  <snomedBranch>MAIN/SNOMEDCT-NL</snomedBranch>
  <stringFormat>[0/0] van [0/1]</stringFormat>
  <!-- bv. 'clinging' intraductaal carcinoom van laterale onderkwadrant van linker mamma -->
  <tags>
    <tag>Complicatie</tag>
  </tags>
  <etl>
    <![CDATA[
           === 116223007 |complicatie (aandoening)| : {
                363698007 |locatie van bevinding (attribuut)| =
                  ([[ @Locatie ]] [[+id (< 442083009 |anatomische of verworven lichaamsstructuur (lichaamsstructuur)|) ]] : {
                      [[ 0..1 @Lateraliteit ]] 272741003 |Laterality| = [[+id(< 182353008 |Side (qualifier value)|) ]]
                      }),
                [[ @Infectie ]] 308489006 |pathologisch proces (kwalificatiewaarde)| =  
                    [[+id (<< 441862004 |infectieus proces (kwalificatiewaarde)|) ]],
				[[ 0..1 @Veroorzaker ]] 246075003 |veroorzaker (attribuut)| =  
                    [[+id (< 410607006 |organisme (organisme)|) ]]	
			}
			{
				[[ @Bij ]] 47429007 |bij (attribuut)| =  
                    [[+id (< 49062001 |hulpmiddel (fysiek object)|) ]]}
			
        ]]>
  </etl>
  <items>
    <item name="Locatie">
      <title>Locatie</title>
      <description>Welke lichaamsstructuur?</description>
    </item>
    <item name="Infectie">
      <title>Infectieus proces</title>
      <description>Infectieus of parasitair proces?</description>
    </item>
	<item name="Veroorzaker">
      <title>Veroorzaker</title>
      <description>Welk organisme is de veroorzaker van de infectie? </description>
    </item>
	<item name="Bij">
      <title>Bij</title>
      <description>Geassocieerd hulpmiddel </description>
    </item>
    <item name="Lateraliteit">
      <title>Lateraliteit</title>
      <description>Welke zijde?</description>
    </item>
  </items>
</template>